README.md
setup.cfg
setup.py
stannp/__init__.py
stannp.egg-info/PKG-INFO
stannp.egg-info/SOURCES.txt
stannp.egg-info/dependency_links.txt
stannp.egg-info/requires.txt
stannp.egg-info/top_level.txt