Metadata-Version: 1.2
Name: stannp
Version: 1.0.0
Summary: An API wrapper for Stannp, a service for sending snail mail via a web api, such as postcards and letters.
Home-page: https://github.com/andy-pi/stannp-api
Author: AndyPi
Author-email: info@andypi.co.uk
License: GNU
Project-URL: Author, https://andypi.co.uk/
Project-URL: Stannp API, https://www.stannp.com/direct-mail-api
Keywords: stannp,postcard,letters,api,snail mail
Platform: UNKNOWN
Classifier: Development Status :: 4 - Beta
Classifier: Programming Language :: Python :: 3
Classifier: License :: OSI Approved :: GNU General Public License v3 (GPLv3)
Requires-Python: >=3
